amsdal_glue_sql_parser/__about__.py
amsdal_glue_sql_parser/__init__.py
amsdal_glue_sql_parser/py.typed
amsdal_glue_sql_parser/parsers/__init__.py
amsdal_glue_sql_parser/parsers/base.py
amsdal_glue_sql_parser/parsers/sqloxide_parser.py
amsdal_glue_sql_parser-0.1.4.dist-info/METADATA
amsdal_glue_sql_parser-0.1.4.dist-info/WHEEL
amsdal_glue_sql_parser-0.1.4.dist-info/licenses/LICENSE.txt
amsdal_glue_sql_parser-0.1.4.dist-info/licenses/NOTICE.txt
amsdal_glue_sql_parser-0.1.4.dist-info/RECORD
